omni_reports/__init__.py
omni_reports/client/__init__.py
omni_reports/client/client.py
omni_reports/client/errors.py
omni_reports/client/fields.py
omni_reports/client/fields_helpers.py
omni_reports/client/models.py
omni_reports/client/resolvers.py
omni_reports/client/schemas.py
omni_reports/client/types.py
omni_reports/client/utils.py
omni_reports/facebook_reports/__init__.py
omni_reports/facebook_reports/base.py
omni_reports/facebook_reports/fields.py
omni_reports/facebook_reports/settings.py
omni_reports/facebook_reports/types.py
omni_reports/google_reports/__init__.py
omni_reports/google_reports/base.py
omni_reports/google_reports/types.py
tests/__init__.py
tests/example_facebook_ads.py
tests/example_google_ads.py
omni_reports-0.0.8.dist-info/LICENSE
omni_reports-0.0.8.dist-info/METADATA
omni_reports-0.0.8.dist-info/WHEEL
omni_reports-0.0.8.dist-info/top_level.txt
omni_reports-0.0.8.dist-info/RECORD
