Metadata-Version: 2.1
Name: omni-reports
Version: 0.0.8
Summary: Omni Report Definition
Home-page: https://github.com/paretogroup/omni-reports
Author: Pareto Group
Author-email: noreply@paretogroup.com.br
License: UNKNOWN
Keywords: pareto,api,reports
Platform: UNKNOWN
